pytorchw/__init__.py
pytorchw/errors.py
pytorchw/extras.py
pytorchw/training.py
pytorchw/utils.py
pytorchw-0.2.0.dist-info/METADATA
pytorchw-0.2.0.dist-info/WHEEL
pytorchw-0.2.0.dist-info/RECORD
